dcode/__init__.py
dcode/__main__.py
dcode/dcode.py
dcode/demo.txt
dcode/install.py
dcode/linux/dcode.desktop
dcode/macos/Right-click and Open DCode to install.txt
dcode/macos/DCode.app/Contents/Info.plist
dcode/macos/DCode.app/Contents/PkgInfo
dcode/macos/DCode.app/Contents/MacOS/applet
dcode/macos/DCode.app/Contents/Resources/applet.icns
dcode/macos/DCode.app/Contents/Resources/applet.rsrc
dcode/macos/DCode.app/Contents/Resources/Scripts/main.scpt
dcode/macos/DCode.app/Contents/Resources/description.rtfd/TXT.rtf
dcode-0.3.0.dist-info/DESCRIPTION.rst
dcode-0.3.0.dist-info/METADATA
dcode-0.3.0.dist-info/RECORD
dcode-0.3.0.dist-info/WHEEL
dcode-0.3.0.dist-info/entry_points.txt
dcode-0.3.0.dist-info/metadata.json
dcode-0.3.0.dist-info/top_level.txt
