Metadata-Version: 2.0
Name: dcode
Version: 0.3.0
Summary: A URL scheme to share code
Home-page: https://github.com/deckardai/dcode
Author: Aurélien Nicolas
Author-email: info@deckard.ai
License: Apache2
Keywords: url code file sharing development
Platform: UNKNOWN
Classifier: Development Status :: 4 - Beta
Classifier: Intended Audience :: Developers
Classifier: Topic :: Software Development
Classifier: License :: OSI Approved :: Apache Software License
Classifier: Programming Language :: Python :: 2
Classifier: Programming Language :: Python :: 2.6
Classifier: Programming Language :: Python :: 2.7
Classifier: Programming Language :: Python :: 3
Classifier: Programming Language :: Python :: 3.3
Classifier: Programming Language :: Python :: 3.4
Classifier: Programming Language :: Python :: 3.5
